acltoolkit/add_groupmember.py
acltoolkit/constants.py
acltoolkit/entry.py
acltoolkit/formatting.py
acltoolkit/get_objectacl.py
acltoolkit/give_dcsync.py
acltoolkit/give_genericall.py
acltoolkit/ldap.py
acltoolkit/set_logon_script.py
acltoolkit/set_objectowner.py
acltoolkit/target.py
acltoolkit_ad-0.2.2.dist-info/LICENSE
acltoolkit_ad-0.2.2.dist-info/METADATA
acltoolkit_ad-0.2.2.dist-info/WHEEL
acltoolkit_ad-0.2.2.dist-info/entry_points.txt
acltoolkit_ad-0.2.2.dist-info/top_level.txt
acltoolkit_ad-0.2.2.dist-info/RECORD
